Metadata-Version: 2.1
Name: Sudoku-py-lib
Version: 1.0.7
Summary: package to generate and solve sudoku puzzles
Home-page: UNKNOWN
Author: Vollinger
Author-email: 
License: Apache 2.0
Platform: UNKNOWN
